setup.py
zen/__init__.py
zen/router.py
zen/gae/__init__.py
zen/gae/middleware/__init__.py
zen/gae/middleware/email_errors.py
zen/gae/middleware/parameter.py
zen/gae/middleware/router_middleware.py
zen/gae/middleware/webapp2_dependencies.py
zenwarch.egg-info/PKG-INFO
zenwarch.egg-info/SOURCES.txt
zenwarch.egg-info/dependency_links.txt
zenwarch.egg-info/not-zip-safe
zenwarch.egg-info/top_level.txt